async_dispatch.py
async_dispatch-0.1.dist-info/DESCRIPTION.rst
async_dispatch-0.1.dist-info/METADATA
async_dispatch-0.1.dist-info/RECORD
async_dispatch-0.1.dist-info/WHEEL
async_dispatch-0.1.dist-info/metadata.json
async_dispatch-0.1.dist-info/top_level.txt
