Metadata-Version: 2.0
Name: async-dispatch
Version: 0.1
Summary: Dispatches events from a publisher to any number of subscribers.
Home-page: https://github.com/tobypatterson/async-dispatch/
Author: Toby Patterson
Author-email: me@tobys.email
License: MIT
Download-URL: http://github.com/tobypatterson/async-dispatch/tarball/master
Keywords: asyncio,events,queue
Platform: UNKNOWN
Classifier: Intended Audience :: Developers
Classifier: Programming Language :: Python :: 3.5
Classifier: Topic :: Communications
